AIR_Bench/AIR_Bench.py
AIR_Bench/__init__.py
AIR_Bench/evaluation_utils/__init__.py
AIR_Bench/evaluation_utils/data_loader.py
AIR_Bench/evaluation_utils/evaluation_arguments.py
AIR_Bench/evaluation_utils/evaluator.py
AIR_Bench/evaluation_utils/searcher.py
AIR_Bench/model_utils/__init__.py
AIR_Bench/model_utils/flag_dres_model.py
AIR_Bench/model_utils/model_arguments.py
AIR_Bench/tasks/__init__.py
AIR_Bench/tasks/long_doc_tasks.py
AIR_Bench/tasks/qa_tasks.py
AIR_Bench/tasks/tasks.py
air-bench/AIR_Bench.py
air-bench/__init__.py
air-bench/evaluation_utils/__init__.py
air-bench/evaluation_utils/data_loader.py
air-bench/evaluation_utils/evaluation_arguments.py
air-bench/evaluation_utils/evaluator.py
air-bench/evaluation_utils/searcher.py
air-bench/model_utils/__init__.py
air-bench/model_utils/flag_dres_model.py
air-bench/model_utils/model_arguments.py
air-bench/tasks/__init__.py
air-bench/tasks/long_doc_tasks.py
air-bench/tasks/qa_tasks.py
air-bench/tasks/tasks.py
airb-0.0.1.dist-info/LICENSE
airb-0.0.1.dist-info/METADATA
airb-0.0.1.dist-info/WHEEL
airb-0.0.1.dist-info/top_level.txt
airb-0.0.1.dist-info/RECORD
