Metadata-Version: 2.1
Name: airb
Version: 0.0.1
Summary: AIR-Bench: Automated Heterogeneous Information Retrieval Benchmark
Home-page: https://github.com/AIR-Bench/AIR-Bench
License-File: LICENSE
Requires-Dist: datasets >=2.18.0
Requires-Dist: mteb >=1.7.17
Requires-Dist: torch >=1.6.0
Requires-Dist: transformers >=4.33.0
